ahsoka/__init__.py
ahsoka/badpix.py
ahsoka/badpix.py.orig
ahsoka/clipping.py
ahsoka/extraction.py
ahsoka/masking.py
ahsoka/niriss_cython.pyx
ahsoka/oneoverf.py
ahsoka/oneoverf_prism.py
ahsoka/prism_background.py
ahsoka/rm_background.py
ahsoka/rm_background_simple.py
ahsoka/soss_clear_background.py
ahsoka/soss_f277w_background.py
ahsoka/spoon_utils.py
ahsoka/tracing.py
ahsoka/utils.py
ahsoka-0.0.2.dist-info/METADATA
ahsoka-0.0.2.dist-info/WHEEL
ahsoka-0.0.2.dist-info/licenses/LICENSE.txt
ahsoka-0.0.2.dist-info/RECORD
